neurop/__init__.py
neurop/base.py
neurop/layers/__init__.py
neurop/layers/iolayers.py
neurop/layers/spectralconv.py
neurop/operators/__init__.py
neurop/operators/fourier.py
neurop/tests/test_fourier.py
neurop/tests/test_iolayers.py
neurop/tests/test_spectralconv.py
neurop-0.0.5.dist-info/METADATA
neurop-0.0.5.dist-info/WHEEL
neurop-0.0.5.dist-info/licenses/LICENSE
neurop-0.0.5.dist-info/RECORD
