Metadata-Version: 2.4
Name: neurop
Version: 0.0.5
Summary: Neural Operators!
Project-URL: Homepage, https://github.com/lonelyneutrin0/neurop
Author-email: Hrishikesh Belagali <belagal1@msu.edu>, Aditya Narayan <ma24btech11001@iith.ac.in>
License-Expression: MIT
License-File: LICENSE
Keywords: machine learning,neural operator
Classifier: Programming Language :: Python :: 3.9
Classifier: Programming Language :: Python :: 3.10
Classifier: Programming Language :: Python :: 3.11
Classifier: Programming Language :: Python :: 3.12
Requires-Python: >=3.9
Requires-Dist: opt-einsum~=3.4.0
Requires-Dist: torch~=2.5.1
Provides-Extra: dev
Requires-Dist: hatchling~=1.27.0; extra == 'dev'
Requires-Dist: mypy~=1.13.0; extra == 'dev'
Requires-Dist: pdoc~=15.0.4; extra == 'dev'
Requires-Dist: pytest~=8.0.2; extra == 'dev'
Requires-Dist: ruff~=0.9.4; extra == 'dev'
Provides-Extra: examples
Requires-Dist: matplotlib~=3.10.3; extra == 'examples'
